{
  "generatedAt": "2026-04-29T14:47:58.923Z",
  "threshold": 0.05,
  "note": "Generated by scripts/check-bundle-size.mjs --write-baseline. Sizes are bytes per chunk-stem (Vite hashed filenames stripped). To intentionally bump after an approved increase, regenerate.",
  "chunks": {
    "InviteAccept": 5357,
    "POD-dialog": 7626,
    "Users": 16371,
    "WorkerLayout": 16731,
    "accounting": 52402,
    "adjustments": 13781,
    "auth": 1277,
    "badge": 663,
    "bom": 164563,
    "button": 1814,
    "cached-fetch": 2617,
    "card": 978,
    "cash-flow": 18035,
    "common": 295,
    "consignment": 28818,
    "constants": 810,
    "create": 74923,
    "credit-notes": 8389,
    "csrf": 348,
    "customers": 42195,
    "dashboard": 14190,
    "data-grid": 50609,
    "debit-notes": 8354,
    "delivery": 96195,
    "delivery-order": 1490,
    "department": 36176,
    "dept": 496,
    "detail": 224883,
    "document-flow-diagram": 3960,
    "e-invoice": 14399,
    "edit": 54959,
    "employees": 100822,
    "fabrics": 8682,
    "fetch-json": 1429,
    "fg-scan": 8481,
    "forecast": 22818,
    "generate-co-pdf": 8525,
    "generate-customer-quotation-pdf": 5083,
    "generate-do-pdf": 4306,
    "generate-grn-pdf": 3632,
    "generate-invoice-pdf": 5383,
    "generate-packing-pdf": 3723,
    "generate-payslip-pdf": 7990,
    "generate-po-pdf": 4343,
    "generate-purchase-order-pdf": 5516,
    "generate-so-pdf": 8545,
    "generate-sticker-pdf": 9009,
    "grn": 15290,
    "health": 3481,
    "icons": 38558,
    "image-compress": 1556,
    "in-transit-8": 26414,
    "index": 69292,
    "index.es": 151422,
    "input": 619,
    "inventory": 77232,
    "invoice": 1784,
    "invoices": 18195,
    "issue": 5075,
    "kv-config": 3459,
    "lock-banner": 545,
    "login": 17358,
    "maintenance": 26542,
    "maintenance-": 19955,
    "me": 9416,
    "mrp": 19547,
    "note": 70648,
    "notifications": 7229,
    "organisations": 8718,
    "overview": 168,
    "pay": 10939,
    "payments": 10313,
    "pdf": 1035800,
    "pdf-utils": 51850,
    "pi": 9534,
    "planning": 30747,
    "presence-banner": 2077,
    "pricing": 17681,
    "pricing-options": 1846,
    "procurement": 19345,
    "production": 74730,
    "products": 50287,
    "purify.es": 21054,
    "qr-utils": 24292,
    "quality": 22352,
    "rd": 30600,
    "rd-project": 1123,
    "react-vendor": 276209,
    "reports": 20845,
    "return": 17689,
    "rolldown-runtime": 685,
    "safe-json": 135,
    "sales": 28757,
    "scan": 160738,
    "scan-po-modal": 28777,
    "scheduler": 1423,
    "schemas": 63573,
    "searchable-select": 3618,
    "service-cases": 18093,
    "service-orders": 22123,
    "settings": 23983,
    "so-category": 427,
    "stock-value": 21562,
    "tabs-context": 8581,
    "toast": 4462,
    "trace": 679,
    "track": 6908,
    "use-form-draft": 1036,
    "use-session-state": 566,
    "use-url-state": 969,
    "utils": 30003,
    "warehouse": 20711,
    "wip-name": 413,
    "worker": 11315,
    "xlsx": 424859
  }
}
